carbon2/__init__.py
carbon2/__pycache__/__init__.cpython-36.pyc
carbon2/__pycache__/__init__.cpython-39.pyc
carbon2/analysis/__init__.py
carbon2/analysis/similarity.py
carbon2/analysis/tfidf.py
carbon2/analysis/__pycache__/__init__.cpython-36.pyc
carbon2/analysis/__pycache__/similarity.cpython-36.pyc
carbon2/analysis/__pycache__/tfidf.cpython-36.pyc
carbon2/api/__init__.py
carbon2/api/download.py
carbon2/api/submit.py
carbon2/api/submit_list.py
carbon2/api/submit_list_table.py
carbon2/api/__pycache__/__init__.cpython-36.pyc
carbon2/api/__pycache__/__init__.cpython-39.pyc
carbon2/api/__pycache__/download.cpython-36.pyc
carbon2/api/__pycache__/submit.cpython-36.pyc
carbon2/api/__pycache__/submit.cpython-39.pyc
carbon2/api/__pycache__/submit_list.cpython-36.pyc
carbon2/api/__pycache__/submit_list_table.cpython-39.pyc
carbon2/datasets/__init__.py
carbon2/datasets/get_country_list.py
carbon2/datasets/get_news_list.py
carbon2/pipeline/__init__.py
carbon2/pipeline/get_page_list.py
carbon2/pipeline/__pycache__/__init__.cpython-36.pyc
carbon2/pipeline/__pycache__/get_page_list.cpython-36.pyc
carbon2-0.0.7.dist-info/LICENSE
carbon2-0.0.7.dist-info/METADATA
carbon2-0.0.7.dist-info/WHEEL
carbon2-0.0.7.dist-info/top_level.txt
carbon2-0.0.7.dist-info/RECORD
