Metadata-Version: 2.1
Name: carbon2
Version: 0.0.7
Summary: Carbon2 system APIs
Author: Donghua Chen
Author-email: douglaschan@126.com
License: MIT
Keywords: carbon2,carbon emission,carbon neutrality,carbon emission
Platform: UNKNOWN
Classifier: Development Status :: 5 - Production/Stable
Classifier: Intended Audience :: Developers
Classifier: Topic :: Software Development :: Build Tools
Classifier: License :: OSI Approved :: MIT License
Classifier: Programming Language :: Python :: 3
Classifier: Programming Language :: Python :: 3.6
Classifier: Programming Language :: Python :: 3.7
Classifier: Programming Language :: Python :: 3.8
Classifier: Programming Language :: Python :: 3.9
Classifier: Programming Language :: Python :: 3 :: Only
Requires-Python: >=3.6, <4
License-File: LICENSE
Requires-Dist: quick-crawler
Requires-Dist: selenium
Requires-Dist: bs4
Requires-Dist: requests
Requires-Dist: tqdm
Requires-Dist: matplotlib
Requires-Dist: wordcloud
Requires-Dist: jieba
Requires-Dist: quick-csv
Requires-Dist: strsimpy
Provides-Extra: dev
Requires-Dist: check-manifest ; extra == 'dev'
Provides-Extra: test
Requires-Dist: coverage ; extra == 'test'
